GameTools/__init__.py
GameTools/Entity/__init__.py
GameTools/Entity/basics.py
GameTools/Entity/shapes.py
GameTools/Templates/FullTemplate.py
GameTools/Templates/ProjectTemplates.py
GameTools/Templates/__init__.py
GameTools/Timing/DeltaTime.py
GameTools/Timing/__init__.py
GameTools/Tools/Messaging.py
GameTools/Tools/__init__.py
GameTools/Tools/Math/Basics.py
GameTools/Tools/Math/__init__.py
GameTools-0.2.0.dist-info/LICENSE.txt
GameTools-0.2.0.dist-info/METADATA
GameTools-0.2.0.dist-info/WHEEL
GameTools-0.2.0.dist-info/top_level.txt
GameTools-0.2.0.dist-info/RECORD
