Metadata-Version: 2.1
Name: GameTools
Version: 0.2.0
Summary: A bunch of tools for making games in Pygame and other libraries.
Home-page: https://github.com/spidertyler2005/GameTools
Author: Spidertyler2005
Author-email: spidertyler1122@gmail.com
License: UNKNOWN
Project-URL: Bug Tracker, https://github.com/spidertyler2005/GameTools/issues
Platform: UNKNOWN
Classifier: Programming Language :: Python :: 3
Classifier: License :: OSI Approved :: MIT License
Classifier: Operating System :: OS Independent
Requires-Python: >=3.8
License-File: LICENSE.txt
Requires-Dist: pygame
